ci/__init__.py
ci/__main__.py
ci/_version.py
ci/constants.py
ci/driver.py
ci/exceptions.py
ci/utils.py
scikit_ci-0.21.0.dist-info/AUTHORS.rst
scikit_ci-0.21.0.dist-info/LICENSE_Apache_20
scikit_ci-0.21.0.dist-info/METADATA
scikit_ci-0.21.0.dist-info/WHEEL
scikit_ci-0.21.0.dist-info/entry_points.txt
scikit_ci-0.21.0.dist-info/top_level.txt
scikit_ci-0.21.0.dist-info/RECORD
