Metadata-Version: 2.1
Name: scikit-ci
Version: 0.21.0
Summary: scikit-ci enables a centralized and simpler CI configuration for Python extensions.
Home-page: https://github.com/scikit-build/scikit-ci
Author: The scikit-build team
Author-email: scikit-build@googlegroups.com
License: Apache
Keywords: CI Appveyor CircleCI Travis
Platform: UNKNOWN
Classifier: Development Status :: 3 - Alpha
Classifier: Environment :: Console
Classifier: Intended Audience :: Developers
Classifier: License :: OSI Approved :: Apache Software License
Classifier: Natural Language :: English
Classifier: Operating System :: OS Independent
Classifier: Programming Language :: Python :: 2
Classifier: Programming Language :: Python :: 2.7
Classifier: Programming Language :: Python :: 3
Classifier: Programming Language :: Python :: 3.3
Classifier: Programming Language :: Python :: 3.4
Classifier: Programming Language :: Python :: 3.5
Classifier: Programming Language :: Python :: 3.6
Classifier: Programming Language :: Python :: 3.7
Classifier: Topic :: Software Development :: Build Tools
Requires-Dist: pyfiglet
Requires-Dist: ruamel.yaml (>=0.15) ; python_version == "2.7"
Requires-Dist: ruamel.yaml (<=0.15.94,>=0.15) ; python_version == "3.4"
Requires-Dist: ruamel.yaml (>=0.15) ; python_version > "3.4"
